envantic/__init__.py
envantic/model.py
envantic/py.typed
envantic-0.1.2.dist-info/WHEEL
envantic-0.1.2.dist-info/METADATA
envantic-0.1.2.dist-info/RECORD
