Metadata-Version: 2.3
Name: envantic
Version: 0.1.2
Summary: Pydantic-powered, type-safe environment variable loader
Keywords: pydantic,environment,config,settings,dotenv
Classifier: Development Status :: 3 - Alpha
Classifier: Intended Audience :: Developers
Classifier: License :: OSI Approved :: MIT License
Classifier: Programming Language :: Python
Classifier: Programming Language :: Python :: 3
Classifier: Programming Language :: Python :: 3 :: Only
Classifier: Programming Language :: Python :: 3.9
Classifier: Programming Language :: Python :: 3.10
Classifier: Programming Language :: Python :: 3.11
Classifier: Programming Language :: Python :: 3.12
Classifier: Typing :: Typed
Requires-Dist: pydantic>=2.0
Requires-Dist: python-dotenv>=1.0.0
Requires-Python: >=3.9
Project-URL: Homepage, https://github.com/c0sogi/envantic
Project-URL: Issues, https://github.com/c0sogi/envantic/issues
